hamiltoncurrentweather/__init__.py
hamiltoncurrentweather_Rx168059-0.1.2.dist-info/LICENSE
hamiltoncurrentweather_Rx168059-0.1.2.dist-info/METADATA
hamiltoncurrentweather_Rx168059-0.1.2.dist-info/WHEEL
hamiltoncurrentweather_Rx168059-0.1.2.dist-info/top_level.txt
hamiltoncurrentweather_Rx168059-0.1.2.dist-info/RECORD
