Metadata-Version: 2.1
Name: hamiltoncurrentweather_Rx168059
Version: 0.1.2
Summary: This package will get information about current weather in hamilton from weatherwatch website
Author-email: Muhammad Dwi Reza <dwireza1002@gmail.com>
Project-URL: Homepage, https://github.com/Rex-Project-Organization/Hamilton-Current-Weather
Classifier: Programming Language :: Python :: 3
Classifier: License :: OSI Approved :: GNU General Public License v3 (GPLv3)
Classifier: Operating System :: OS Independent
Classifier: Development Status :: 4 - Beta
Requires-Python: >=3.12
License-File: LICENSE
